aegis_vault/__init__.py
aegis_vault/middleware.py
aegis_vault-0.1.1.dist-info/licenses/LICENSE
aegis_vault-0.1.1.dist-info/METADATA
aegis_vault-0.1.1.dist-info/WHEEL
aegis_vault-0.1.1.dist-info/top_level.txt
aegis_vault-0.1.1.dist-info/RECORD
