Metadata-Version: 2.4
Name: aegis-vault
Version: 0.1.1
Summary: Secure, LGPD-compliant middleware for protecting sensitive data in LLM prompts
Home-page: https://github.com/cbuchele/aegis-vault
Author: cbuchele
Author-email: cbuchele <contact@aegisai.com.br>
License: Apache-2.0
Project-URL: Homepage, https://github.com/cbuchele/aegis-vault
Project-URL: Documentation, https://github.com/cbuchele/aegis-vault#readme
Classifier: Development Status :: 3 - Alpha
Classifier: Intended Audience :: Developers
Classifier: License :: OSI Approved :: Apache Software License
Classifier: Programming Language :: Python :: 3
Classifier: Programming Language :: Python :: 3.8
Classifier: Programming Language :: Python :: 3.9
Classifier: Programming Language :: Python :: 3.10
Classifier: Programming Language :: Python :: 3.11
Classifier: Topic :: Security
Classifier: Topic :: Software Development :: Libraries :: Python Modules
Requires-Python: >=3.8
License-File: LICENSE
Requires-Dist: cryptography>=3.4.7
Requires-Dist: spacy>=3.0.0
Provides-Extra: dev
Requires-Dist: pytest>=6.0; extra == "dev"
Requires-Dist: black>=21.12b0; extra == "dev"
Requires-Dist: isort>=5.10.1; extra == "dev"
Requires-Dist: flake8>=4.0.1; extra == "dev"
Requires-Dist: mypy>=0.910; extra == "dev"
Dynamic: author
Dynamic: home-page
Dynamic: license-file
Dynamic: requires-python
